odoo/addons/repair_quality_control_issue/README.rst
odoo/addons/repair_quality_control_issue/__init__.py
odoo/addons/repair_quality_control_issue/__manifest__.py
odoo/addons/repair_quality_control_issue/i18n/repair_quality_control_issue.pot
odoo/addons/repair_quality_control_issue/models/__init__.py
odoo/addons/repair_quality_control_issue/models/qc_issue.py
odoo/addons/repair_quality_control_issue/models/repair_order.py
odoo/addons/repair_quality_control_issue/readme/CONTRIBUTORS.rst
odoo/addons/repair_quality_control_issue/readme/DESCRIPTION.rst
odoo/addons/repair_quality_control_issue/readme/USAGE.rst
odoo/addons/repair_quality_control_issue/static/description/icon.png
odoo/addons/repair_quality_control_issue/static/description/index.html
odoo/addons/repair_quality_control_issue/views/qc_issue_views.xml
odoo/addons/repair_quality_control_issue/views/repair_order_views.xml
odoo/addons/repair_quality_control_issue/wizards/__init__.py
odoo/addons/repair_quality_control_issue/wizards/qc_issue_make_repair.py
odoo/addons/repair_quality_control_issue/wizards/qc_issue_make_repair_views.xml
odoo12_addon_repair_quality_control_issue-12.0.1.0.1.dist-info/METADATA
odoo12_addon_repair_quality_control_issue-12.0.1.0.1.dist-info/WHEEL
odoo12_addon_repair_quality_control_issue-12.0.1.0.1.dist-info/top_level.txt
odoo12_addon_repair_quality_control_issue-12.0.1.0.1.dist-info/RECORD
