Metadata-Version: 2.1
Name: odoo12-addon-repair-quality-control-issue
Version: 12.0.1.0.1
Summary: Add the possibility to create repairs orders from quality control issues.
Home-page: https://github.com/OCA/manufacture
Author: Trey, Odoo Community Association (OCA)
Author-email: support@odoo-community.org
License: LGPL-3
Platform: UNKNOWN
Classifier: Programming Language :: Python
Classifier: Framework :: Odoo
Classifier: Framework :: Odoo :: 12.0
Classifier: License :: OSI Approved :: GNU Lesser General Public License v3 (LGPLv3)
Requires-Python: >=3.5
Requires-Dist: odoo12-addon-quality-control-issue
Requires-Dist: odoo (<12.1dev,>=12.0a)
